kaltura_uploader/__init__.py
kaltura_uploader/cli.py
kaltura_uploader/constants.py
kaltura_uploader/decorators.py
kaltura_uploader/logging_config.py
kaltura_uploader/mime_utils.py
kaltura_uploader/uploader.py
tests/__init__.py
tests/test_library_mode.py
tests/test_mime_utils.py
tests/test_uploader.py
kaltura_uploader-0.1.3.dist-info/METADATA
kaltura_uploader-0.1.3.dist-info/WHEEL
kaltura_uploader-0.1.3.dist-info/entry_points.txt
kaltura_uploader-0.1.3.dist-info/top_level.txt
kaltura_uploader-0.1.3.dist-info/RECORD
