Metadata-Version: 2.4
Name: kaltura_uploader
Version: 0.1.3
Summary: A robust Python tool for uploading files to Kaltura with chunked and adaptive upload support, automatic MIME type detection, and entry creation.
Home-page: https://github.com/zoharbabin/kaltura_uploader
Author: Zohar Babin
Author-email: zohar.babin@kaltura.com
License: MIT
Project-URL: Bug Tracker, https://github.com/zoharbabin/kaltura_uploader/issues
Project-URL: Documentation, https://github.com/zoharbabin/kaltura_uploader#readme
Keywords: kaltura,upload,chunked,adaptive,video,media,file,cli
Classifier: Development Status :: 4 - Beta
Classifier: Intended Audience :: Developers
Classifier: Topic :: Software Development :: Libraries
Classifier: License :: OSI Approved :: MIT License
Classifier: Operating System :: OS Independent
Classifier: Programming Language :: Python :: 3
Requires-Python: >=3.10
Requires-Dist: python-dotenv
Requires-Dist: python-magic
Requires-Dist: colorlog
Requires-Dist: requests
Requires-Dist: requests-toolbelt
Requires-Dist: KalturaApiClient
Requires-Dist: lxml
Provides-Extra: test
Requires-Dist: pytest; extra == "test"
